euphonic-1.5.1.dist-info/METADATA
euphonic-1.5.1.dist-info/WHEEL
euphonic-1.5.1.dist-info/entry_points.txt
euphonic/_euphonic.cpython-312-darwin.so
euphonic/__init__.py
euphonic/brille.py
euphonic/broadening.py
euphonic/crystal.py
euphonic/debye_waller.py
euphonic/force_constants.py
euphonic/io.py
euphonic/plot.py
euphonic/powder.py
euphonic/qpoint_frequencies.py
euphonic/qpoint_phonon_modes.py
euphonic/sampling.py
euphonic/structure_factor.py
euphonic/ureg.py
euphonic/util.py
euphonic/validate.py
euphonic/cli/__init__.py
euphonic/cli/brille_convergence.py
euphonic/cli/dispersion.py
euphonic/cli/dos.py
euphonic/cli/intensity_map.py
euphonic/cli/optimise_dipole_parameter.py
euphonic/cli/powder_map.py
euphonic/cli/show_sampling.py
euphonic/cli/utils.py
euphonic/data/__init__.py
euphonic/data/bluebook.json
euphonic/data/sears-1992.json
euphonic/data/reciprocal_spectroscopy_definitions.txt
euphonic/readers/__init__.py
euphonic/readers/castep.py
euphonic/readers/phonopy.py
euphonic/spectra/__init__.py
euphonic/spectra/base.py
euphonic/spectra/collections.py
euphonic/styles/__init__.py
euphonic/styles/base.mplstyle
euphonic/styles/intensity_widget.mplstyle
euphonic/writers/__init__.py
euphonic/writers/phonon_website.py
euphonic/version.py
euphonic/CITATION.cff
euphonic/LICENSE
euphonic-1.5.1.dist-info/RECORD
