Metadata-Version: 2.1
Name: Euphonic
Version: 1.5.1
Summary: Euphonic calculates phonon bandstructures and inelastic neutron scattering intensities from modelling code output (e.g. CASTEP)
Keywords: Python,physics,phonons,inelastic neutron scattering,CASTEP,Phonopy,force constants
License: GPLv3
Classifier: Development Status :: 4 - Beta
Classifier: Environment :: Console
Classifier: Intended Audience :: Science/Research
Classifier: License :: OSI Approved :: GNU General Public License v3 (GPLv3)
Classifier: Programming Language :: C
Classifier: Programming Language :: Python :: 3
Classifier: Topic :: Scientific/Engineering :: Physics
Project-URL: Homepage, https://github.com/pace-neutrons/Euphonic
Project-URL: Repository, https://github.com/pace-neutrons/Euphonic.git
Project-URL: Bug Tracker, https://github.com/pace-neutrons/Euphonic/issues
Project-URL: documentation, https://euphonic.readthedocs.io/en/stable/
Requires-Python: >=3.10
Requires-Dist: packaging
Requires-Dist: numpy>=1.24.0
Requires-Dist: scipy>=1.10
Requires-Dist: seekpath>=1.1.0
Requires-Dist: spglib>=2.1.0
Requires-Dist: pint>=0.22
Requires-Dist: threadpoolctl>=3.0.0
Requires-Dist: toolz>=0.12.1
Provides-Extra: matplotlib
Requires-Dist: matplotlib>=3.8.0; extra == "matplotlib"
Provides-Extra: phonopy-reader
Requires-Dist: h5py>=3.6.0; extra == "phonopy-reader"
Requires-Dist: PyYAML>=6.0; extra == "phonopy-reader"
Provides-Extra: phonopy-reader
Requires-Dist: h5py>=3.6.0; extra == "phonopy-reader"
Requires-Dist: PyYAML>=6.0; extra == "phonopy-reader"
Provides-Extra: brille
Requires-Dist: brille>=0.7.0; extra == "brille"
Provides-Extra: test
Requires-Dist: mock; extra == "test"
Requires-Dist: pytest<9.0,>=8.0; extra == "test"
Requires-Dist: pytest-cov; extra == "test"
Requires-Dist: pytest-mock; extra == "test"
Requires-Dist: pytest-lazy-fixtures; extra == "test"
Requires-Dist: pytest-xdist; extra == "test"
Requires-Dist: pytest-xvfb; extra == "test"
Requires-Dist: python-slugify; extra == "test"
Provides-Extra: ci
Requires-Dist: tox==4.30.3; extra == "ci"
